quart_motor/__init__.py
quart_motor/helpers.py
quart_motor/wrappers.py
tests/__init__.py
tests/quart_motor_tests/__init__.py
tests/quart_motor_tests/test_connection.py
tests/quart_motor_tests/test_wrappers.py
Quart_Motor-2.4.7.dist-info/LICENSE
Quart_Motor-2.4.7.dist-info/METADATA
Quart_Motor-2.4.7.dist-info/WHEEL
Quart_Motor-2.4.7.dist-info/top_level.txt
Quart_Motor-2.4.7.dist-info/RECORD
