Metadata-Version: 2.1
Name: Quart-Motor
Version: 2.4.7
Summary: Motor support for Quart applications
Home-page: https://www.github.com/marirs/quart-motor/
Author: Sriram G
Author-email: marirs@gmail.com
License: BSD
Download-URL: https://www.github.com/marirs/quart-motor/tags
Platform: UNKNOWN
Classifier: Environment :: Web Environment
Classifier: Development Status :: 5 - Production/Stable
Classifier: Natural Language :: English
Classifier: Intended Audience :: Developers
Classifier: License :: OSI Approved :: BSD License
Classifier: Operating System :: MacOS :: MacOS X
Classifier: Operating System :: Unix
Classifier: Programming Language :: Python :: 3.6
Classifier: Programming Language :: Python :: 3.7
Classifier: Programming Language :: Python :: 3.8
Classifier: Topic :: Internet :: WWW/HTTP :: Dynamic Content
Classifier: Topic :: Software Development :: Libraries :: Python Modules
Requires-Python: >=3.6
License-File: LICENSE
Requires-Dist: PyMongo (>=3.10)
Requires-Dist: Quart (>=0.18.0)
Requires-Dist: motor (>=2.1.0)
Requires-Dist: six
Requires-Dist: werkzeug
